legenddataflowscripts/__init__.py
legenddataflowscripts/_version.py
legenddataflowscripts/par/__init__.py
legenddataflowscripts/par/geds/__init__.py
legenddataflowscripts/par/geds/dsp/__init__.py
legenddataflowscripts/par/geds/dsp/dplms.py
legenddataflowscripts/par/geds/dsp/eopt.py
legenddataflowscripts/par/geds/dsp/evtsel.py
legenddataflowscripts/par/geds/dsp/nopt.py
legenddataflowscripts/par/geds/dsp/pz.py
legenddataflowscripts/par/geds/dsp/svm.py
legenddataflowscripts/par/geds/dsp/svm_build.py
legenddataflowscripts/par/geds/hit/__init__.py
legenddataflowscripts/par/geds/hit/aoe.py
legenddataflowscripts/par/geds/hit/ecal.py
legenddataflowscripts/par/geds/hit/lq.py
legenddataflowscripts/par/geds/hit/qc.py
legenddataflowscripts/tier/__init__.py
legenddataflowscripts/tier/dsp.py
legenddataflowscripts/tier/hit.py
legenddataflowscripts/utils/__init__.py
legenddataflowscripts/utils/alias_table.py
legenddataflowscripts/utils/cfgtools.py
legenddataflowscripts/utils/convert_np.py
legenddataflowscripts/utils/log.py
legenddataflowscripts/utils/plot_dict.py
legenddataflowscripts/utils/pulser_removal.py
legenddataflowscripts/workflow/__init__.py
legenddataflowscripts/workflow/execenv.py
legenddataflowscripts/workflow/filedb.py
legenddataflowscripts/workflow/pre_compile_catalog.py
legenddataflowscripts/workflow/utils.py
legend_dataflow_scripts-0.2.1.dist-info/METADATA
legend_dataflow_scripts-0.2.1.dist-info/WHEEL
legend_dataflow_scripts-0.2.1.dist-info/entry_points.txt
legend_dataflow_scripts-0.2.1.dist-info/top_level.txt
legend_dataflow_scripts-0.2.1.dist-info/RECORD
