Metadata-Version: 2.4
Name: legend-dataflow-scripts
Version: 0.2.1
Summary: Python package for the processing scripts for LEGEND-200 data
Author-email: George Marshall <ggmarsh@uw.edu>, Luigi Pertoldi <gipert@pm.me>
Maintainer: The LEGEND Collaboration
Classifier: Development Status :: 4 - Beta
Classifier: Intended Audience :: Developers
Classifier: Intended Audience :: Science/Research
Classifier: License :: OSI Approved :: MIT License
Classifier: Operating System :: MacOS
Classifier: Operating System :: POSIX
Classifier: Operating System :: Unix
Classifier: Programming Language :: Python
Classifier: Programming Language :: Python :: 3
Classifier: Programming Language :: Python :: 3 :: Only
Classifier: Topic :: Scientific/Engineering
Requires-Python: >=3.11
Requires-Dist: colorlog
Requires-Dist: dbetto>=1.2.3
Requires-Dist: pygama>=2.1
Requires-Dist: dspeed>=1.6
Requires-Dist: pylegendmeta>=1.2.5
Requires-Dist: legend-pydataobj>=1.11
Requires-Dist: legend-daq2lh5>=1.6.1
Requires-Dist: pip
Provides-Extra: test
Requires-Dist: legend-dataflow-scripts; extra == "test"
Requires-Dist: pytest>=6; extra == "test"
Requires-Dist: pytest-cov>=3; extra == "test"
Provides-Extra: dev
Requires-Dist: legend-dataflow-scripts[test]; extra == "dev"
Requires-Dist: pre-commit; extra == "dev"
Provides-Extra: docs
Requires-Dist: sphinx>=7.0; extra == "docs"
Requires-Dist: myst_parser>=0.13; extra == "docs"
Requires-Dist: sphinx_inline_tabs; extra == "docs"
Requires-Dist: sphinx_copybutton; extra == "docs"
Requires-Dist: sphinx_autodoc_typehints; extra == "docs"
Requires-Dist: furo>=2023.08.17; extra == "docs"
